mlflow_vizmod/__init__.py
mlflow_vizmod-1.1.3.dist-info/LICENSE
mlflow_vizmod-1.1.3.dist-info/METADATA
mlflow_vizmod-1.1.3.dist-info/WHEEL
mlflow_vizmod-1.1.3.dist-info/entry_points.txt
mlflow_vizmod-1.1.3.dist-info/top_level.txt
mlflow_vizmod-1.1.3.dist-info/RECORD
