Metadata-Version: 2.1
Name: mlflow-vizmod
Version: 1.1.3
Summary: MLflow model flavor for managing visualizations as models
Home-page: UNKNOWN
Author: James Hibbard, Andrew Bauman
License: MIT
Platform: UNKNOWN
Classifier: Programming Language :: Python :: 3.8
Classifier: License :: OSI Approved :: MIT License
Requires-Python: >=3.7
Requires-Dist: mlflow (>=1.11.0)
Requires-Dist: PyYAML (>=5.3.1)
Requires-Dist: altair (>=4.1.0)
Requires-Dist: altair-viewer (>=0.3.0)
